fastapi_controllers/__init__.py
fastapi_controllers/controllers.py
fastapi_controllers/definitions.py
fastapi_controllers/helpers.py
fastapi_controllers/routing.py
fastapi_controllers-0.3.0.dist-info/METADATA
fastapi_controllers-0.3.0.dist-info/WHEEL
fastapi_controllers-0.3.0.dist-info/LICENSE
fastapi_controllers-0.3.0.dist-info/RECORD
