Metadata-Version: 2.1
Name: fastapi-controllers
Version: 0.3.0
Summary: Simple Controller implementation for FastAPI
Home-page: https://github.com/goraje/fastapi-controllers
License: MIT
Keywords: fastapi,controller,cbv,routing
Author: Jerzy Góra
Author-email: j.gora89@gmail.com
Requires-Python: >=3.8,<4.0
Classifier: Framework :: FastAPI
Classifier: License :: OSI Approved :: MIT License
Classifier: Operating System :: MacOS :: MacOS X
Classifier: Operating System :: Microsoft :: Windows
Classifier: Operating System :: POSIX
Classifier: Programming Language :: Python :: 3
Classifier: Programming Language :: Python :: 3.8
Classifier: Programming Language :: Python :: 3.9
Classifier: Programming Language :: Python :: 3.10
Classifier: Programming Language :: Python :: 3.11
Classifier: Topic :: Software Development :: Libraries
Requires-Dist: fastapi
Project-URL: Repository, https://github.com/goraje/fastapi-controllers
